govuk_onelogin_django/__init__.py
govuk_onelogin_django/admin.py
govuk_onelogin_django/apps.py
govuk_onelogin_django/backends.py
govuk_onelogin_django/constants.py
govuk_onelogin_django/models.py
govuk_onelogin_django/types.py
govuk_onelogin_django/urls.py
govuk_onelogin_django/utils.py
govuk_onelogin_django/views.py
govuk_onelogin_django/migrations/__init__.py
govuk_onelogin_django/tests/__init__.py
govuk_onelogin_django/tests/test_backends.py
govuk_onelogin_django/tests/test_settings.py
govuk_onelogin_django/tests/test_utils.py
govuk_onelogin_django/tests/test_views.py
govuk_onelogin_django/tests/urls.py
govuk_onelogin_django-0.4.5.dist-info/METADATA
govuk_onelogin_django-0.4.5.dist-info/WHEEL
govuk_onelogin_django-0.4.5.dist-info/licenses/LICENSE
govuk_onelogin_django-0.4.5.dist-info/RECORD
