Metadata-Version: 2.4
Name: govuk-onelogin-django
Version: 0.4.5
Summary: OpenID Connect client that works with GOV.UK One Login
Project-URL: homepage, https://github.com/uktrade/govuk-onelogin-django
Project-URL: source, https://github.com/uktrade/govuk-onelogin-django
Project-URL: releasenotes, https://github.com/uktrade/govuk-onelogin-django/releases
Project-URL: issues, https://github.com/uktrade/govuk-onelogin-django/issues
Author-email: Matthew Holmes <matthew.holmes@digital.trade.gov.uk>
Maintainer-email: Matthew Holmes <matthew.holmes@digital.trade.gov.uk>
License: MIT License
License-File: LICENSE
Keywords: GOV.UK One Login,OpenID Connect
Classifier: Development Status :: 4 - Beta
Classifier: Intended Audience :: Developers
Classifier: License :: OSI Approved :: MIT License
Classifier: Programming Language :: Python :: 3
Classifier: Programming Language :: Python :: 3.11
Classifier: Programming Language :: Python :: 3.12
Classifier: Programming Language :: Python :: 3.13
Classifier: Topic :: Software Development
Requires-Python: >=3.11
Requires-Dist: authlib==1.6.5
Requires-Dist: django>=4.2
Requires-Dist: requests>=2.32.4
